toolstr/__init__.py
toolstr/py.typed
toolstr/spec.py
toolstr/buffers/__init__.py
toolstr/buffers/stdout_utils.py
toolstr/charts/README.md
toolstr/charts/__init__.py
toolstr/charts/braille_utils.py
toolstr/charts/char_dicts.py
toolstr/charts/grid_utils.py
toolstr/charts/line_utils.py
toolstr/charts/plot_utils.py
toolstr/charts/raster_utils.py
toolstr/charts/render_utils.py
toolstr/charts/sextant_utils.py
toolstr/formats/__init__.py
toolstr/formats/bullet_formats.py
toolstr/formats/column_formats.py
toolstr/formats/datatype_formats.py
toolstr/formats/positional_formats.py
toolstr/formats/rich_formats.py
toolstr/formats/template_formats.py
toolstr/outlines/__init__.py
toolstr/outlines/outline_chars.py
toolstr/outlines/outline_printing.py
toolstr/summaries/__init__.py
toolstr/summaries/nested_summary.py
toolstr/summaries/set_summary.py
toolstr/tables/__init__.py
toolstr/tables/multiline_tables.py
toolstr/tables/table_adapters.py
toolstr/tables/table_utils.py
toolstr-0.9.12.dist-info/licenses/LICENSE
toolstr-0.9.12.dist-info/WHEEL
toolstr-0.9.12.dist-info/METADATA
toolstr-0.9.12.dist-info/RECORD
