Metadata-Version: 2.4
Name: toolstr
Version: 0.9.12
Summary: toolstr is a suite of str processing tools, including formatting and drawing
Requires-Python: >=3.7
License-File: LICENSE
Requires-Dist: tooltime>=0.2.10
Requires-Dist: typing-extensions>=4.0.0
Requires-Dist: scikit-image>=0.19.2 ; extra == "full"
Requires-Dist: rich>=12.1.0 ; extra == "full"
Requires-Dist: scikit-image>=0.19.2 ; extra == "performance"
Requires-Dist: rich>=12.1.0 ; extra == "styling"
Project-URL: Source, https://github.com/sslivkoff/toolstr
Provides-Extra: full
Provides-Extra: performance
Provides-Extra: styling
